dakara_player_vlc/__init__.py
dakara_player_vlc/__main__.py
dakara_player_vlc/background_loader.py
dakara_player_vlc/dakara_manager.py
dakara_player_vlc/dakara_player_vlc.py
dakara_player_vlc/dakara_server.py
dakara_player_vlc/font_loader.py
dakara_player_vlc/resources_manager.py
dakara_player_vlc/state_manager.py
dakara_player_vlc/text_generator.py
dakara_player_vlc/version.py
dakara_player_vlc/vlc_player.py
dakara_player_vlc/commands/__init__.py
dakara_player_vlc/commands/play.py
dakara_player_vlc/resources/__init__.py
dakara_player_vlc/resources/font-awesome.json
dakara_player_vlc/resources/player_vlc.yaml
dakara_player_vlc/resources/backgrounds/__init__.py
dakara_player_vlc/resources/backgrounds/idle.png
dakara_player_vlc/resources/backgrounds/transition.png
dakara_player_vlc/resources/fonts/Roboto-Light.ttf
dakara_player_vlc/resources/fonts/Roboto-Thin.ttf
dakara_player_vlc/resources/fonts/__init__.py
dakara_player_vlc/resources/fonts/fontawesome-webfont.ttf
dakara_player_vlc/resources/templates/__init__.py
dakara_player_vlc/resources/templates/idle.ass
dakara_player_vlc/resources/templates/transition.ass
dakaraplayervlc-1.6.0.dist-info/LICENSE
dakaraplayervlc-1.6.0.dist-info/METADATA
dakaraplayervlc-1.6.0.dist-info/WHEEL
dakaraplayervlc-1.6.0.dist-info/entry_points.txt
dakaraplayervlc-1.6.0.dist-info/top_level.txt
dakaraplayervlc-1.6.0.dist-info/RECORD
