Metadata-Version: 2.1
Name: dakaraplayervlc
Version: 1.6.0
Summary: Player based on VLC for the Dakara Project
Home-page: https://github.com/DakaraProject/dakara-player-vlc
Author: Flore <flore.love@gmail.com>, Neraste <neraste.herr10@gmail.com>
License: MIT
Project-URL: Bug tracker, https://github.com/DakaraProject/dakara-player-vlc/issues
Platform: UNKNOWN
Classifier: License :: OSI Approved :: MIT License
Classifier: Programming Language :: Python
Classifier: Programming Language :: Python :: 3
Classifier: Programming Language :: Python :: 3.5
Classifier: Programming Language :: Python :: 3.6
Classifier: Operating System :: OS Independent
Classifier: Environment :: X11 Applications
Classifier: Environment :: Win32 (MS Windows)
Classifier: Intended Audience :: End Users/Desktop
Requires-Dist: dakarabase (<1.3.0,>=1.2.0)
Requires-Dist: filetype (<1.1.0,>=1.0.7)
Requires-Dist: Jinja2 (<2.11.0,>=2.10.1)
Requires-Dist: python-vlc (<3.1.0,>=3.0.7110)
Provides-Extra: tests
Requires-Dist: codecov ; extra == 'tests'
Requires-Dist: coverage ; extra == 'tests'
Requires-Dist: flake8 ; extra == 'tests'
Requires-Dist: func-timeout ; extra == 'tests'
Requires-Dist: black (==19.10b0) ; (python_version >= "3.6") and extra == 'tests'
